{
  "$schema": "https://schema.management.azure.com/schemas/2015-01-01/deploymentParameters.json#",
  "contentVersion": "1.0.0.0",
  "parameters": {
    "location": {
      "value": "canadacentral"
    },
    "osDiskType": {
      "value": "Premium_LRS"
    },
    "virtualNetworkId": {
      "value": "/subscriptions/f443ea42-ca4a-48d5-98a1-a7358351cec3/resourceGroups/Thom_RG/providers/Microsoft.Network/virtualNetworks/Vlan"
    },
    "virtualNetworkName": {
      "value": "Vlan"
    },
    "networkSecurityGroups": {
      "value": [
        {
          "name": "basicNsgVlan-nic01",
          "id": "/subscriptions/f443ea42-ca4a-48d5-98a1-a7358351cec3/resourceGroups/Thom_RG/providers/Microsoft.Network/networkSecurityGroups/basicNsgVlan-nic01",
          "rules": []
        }
      ]
    },
    "networkInterfaceConfigurations": {
      "value": [
        {
          "name": "Vlan-nic01",
          "primary": true,
          "subnetId": "/subscriptions/f443ea42-ca4a-48d5-98a1-a7358351cec3/resourceGroups/Thom_RG/providers/Microsoft.Network/virtualNetworks/Vlan/subnets/default",
          "applicationGatewayBackendAddressPools": [],
          "loadBalancerBackendAddressPools": [],
          "applicationSecurityGroups": [],
          "loadBalancerInboundNatPools": [],
          "enableAcceleratedNetworking": false,
          "nsgName": "basicNsgVlan-nic01",
          "nsgId": "/subscriptions/f443ea42-ca4a-48d5-98a1-a7358351cec3/resourceGroups/Thom_RG/providers/Microsoft.Network/networkSecurityGroups/basicNsgVlan-nic01",
          "pipName": "publicIp-Vlan-nic01"
        }
      ]
    },
    "vmName": {
      "value": "VMSS-1erDevoir"
    },
    "virtualMachineScaleSetName": {
      "value": "VMSS-1erDevoir"
    },
    "instanceCount": {
      "value": "2"
    },
    "instanceSize": {
      "value": "Standard_B1ls"
    },
    "platformFaultDomainCount": {
      "value": "1"
    },
    "scaleInPolicy": {
      "value": {
        "rules": [
          "Default"
        ],
        "forceDeletion": false
      }
    },
    "upgradePolicy": {
      "value": "Manual"
    },
    "hibernationEnabled": {
      "value": false
    },
    "adminUsername": {
      "value": "unclethom18"
    },
    "adminPassword": {
      "value": null
    },
    "vnetLocation": {
      "value": "canadacentral"
    },
    "vnetExtendedLocation": {
      "value": {}
    },
    "vnetVirtualNetworkName": {
      "value": "Vlan"
    },
    "vnetTagsByResource": {
      "value": {}
    },
    "vnetProperties": {
      "value": {
        "provisioningState": "Succeeded",
        "resourceGuid": "6aa38750-86e1-4b94-b543-8056f507f814",
        "addressSpace": {
          "addressPrefixes": [
            "10.0.0.0/16"
          ]
        },
        "subnets": [
          {
            "name": "default",
            "properties": {
              "provisioningState": "Succeeded",
              "addressPrefix": "10.0.0.0/24",
              "delegations": [],
              "privateEndpointNetworkPolicies": "Disabled",
              "privateLinkServiceNetworkPolicies": "Enabled"
            }
          },
          {
            "name": "AzureBastionSubnet",
            "properties": {
              "provisioningState": "Succeeded",
              "addressPrefix": "10.0.200.0/26",
              "delegations": [],
              "privateEndpointNetworkPolicies": "Disabled",
              "privateLinkServiceNetworkPolicies": "Enabled"
            }
          },
          {
            "name": "snet-canadacentral-1",
            "properties": {
              "addressPrefixes": [
                "10.0.1.0/24"
              ]
            }
          }
        ],
        "virtualNetworkPeerings": [],
        "enableDdosProtection": false
      }
    },
    "vnetNatGatewaysWithNewPublicIpAddress": {
      "value": []
    },
    "vnetNatGatewaysWithoutNewPublicIpAddress": {
      "value": []
    },
    "vnetNatGatewayPublicIpAddressesNewNames": {
      "value": []
    },
    "vnetNetworkSecurityGroupsNew": {
      "value": []
    },
    "vnetResourceGroupName": {
      "value": "Thom_RG"
    },
    "vnetDeploymentName": {
      "value": "network-interface-associated-virtual-network-20241104191856"
    }
  }
}